{
  "id": "117f25bb-6136-49ba-aef8-865c4d9fd601",
  "nickname": "Ca6aka",
  "password": "$2b$10$MNgnDbNDq8XbGzZQB4nUl.hLgDWbgHjShiJ4Qu8bZ9fdpocrxcF/e",
  "balance": 22800,
  "level": 3,
  "experience": 285,
  "totalEarnings": 14800,
  "totalSpent": 0,
  "avatar": {
    "gradient": "from-purple-500 via-pink-500 via-red-500 via-yellow-500 via-green-500 via-blue-500 to-purple-500",
    "pattern": "rainbow-super-admin",
    "seed": 999999,
    "animation": "rainbow-pulse"
  },
  "serverLimit": 3,
  "tutorialCompleted": true,
  "admin": 1,
  "banned": false,
  "muted": false,
  "muteExpires": null,
  "isOnline": true,
  "lastIncomeUpdate": 1755321664028,
  "jobCooldowns": {
    "maintenance": 1755324786386,
    "optimization": 1755324599368,
    "security-audit": 1755325030968
  },
  "currentLearning": null,
  "activities": [
    {
      "id": "866b5f75-d1a7-455a-9b82-5f017f8081da",
      "description": "Completed Server Maintenance (+$150, +10 XP)",
      "timestamp": "8/16/2025, 6:08:06 AM"
    },
    {
      "id": "ebe1d622-b5a0-47cf-b52d-42d1854220a1",
      "description": "Completed Security Audit (+$500, +25 XP)",
      "timestamp": "8/16/2025, 6:07:10 AM"
    },
    {
      "id": "e35db05c-aaf5-421a-9be0-9037ba449534",
      "description": "Completed Performance Optimization (+$250, +18 XP)",
      "timestamp": "8/16/2025, 6:02:29 AM"
    },
    {
      "id": "ab8ebcd2-acec-46ef-b7f3-c309627c3638",
      "description": "Completed Server Maintenance (+$150, +10 XP)",
      "timestamp": "8/16/2025, 6:02:28 AM"
    },
    {
      "id": "1967f01a-aa2e-48f9-a53f-17e1c3292988",
      "description": "Completed Security Audit (+$500, +25 XP) - Level Up! Now level 3",
      "timestamp": "8/16/2025, 5:56:14 AM"
    }
  ],
  "achievements": [],
  "completedJobsCount": 17,
  "completedCoursesCount": 0,
  "dailyQuests": [
    {
      "id": "daily-maintenance-Sat Aug 16 2025",
      "title": "Daily Maintenance",
      "description": "Complete 3 Server Maintenance jobs",
      "reward": 2000,
      "requirement": {
        "type": "job",
        "jobType": "maintenance",
        "count": 3
      },
      "progress": 3,
      "completed": true,
      "date": "Sat Aug 16 2025",
      "claimed": true
    },
    {
      "id": "daily-income-Sat Aug 16 2025",
      "title": "Passive Income",
      "description": "Earn $5,000 from server income",
      "reward": 1500,
      "requirement": {
        "type": "income",
        "amount": 5000
      },
      "progress": 0,
      "completed": false,
      "date": "Sat Aug 16 2025"
    },
    {
      "id": "daily-optimization-Sat Aug 16 2025",
      "title": "Server Optimization",
      "description": "Complete 2 Performance Optimization jobs",
      "reward": 3000,
      "requirement": {
        "type": "job",
        "jobType": "optimization",
        "count": 2
      },
      "progress": 2,
      "completed": true,
      "date": "Sat Aug 16 2025",
      "claimed": true
    }
  ],
  "lastQuestReset": 1755321664028,
  "lastSeen": 1755324930174
}